taskiq_ydb/__init__.py
taskiq_ydb/broker.py
taskiq_ydb/exceptions.py
taskiq_ydb/py.typed
taskiq_ydb/result_backend.py
taskiq_ydb/schedule_source.py
taskiq_ydb-0.4.0.dist-info/licenses/LICENSE
taskiq_ydb-0.4.0.dist-info/WHEEL
taskiq_ydb-0.4.0.dist-info/METADATA
taskiq_ydb-0.4.0.dist-info/RECORD
