Metadata-Version: 2.4
Name: taskiq-ydb
Version: 0.4.0
Summary: YDB integration for taskiq
Keywords: taskiq,tasks,distributed,async,ydb
Author: Anfimov Dima
Author-email: Anfimov Dima <lovesolaristics@gmail.com>
License-Expression: MIT
License-File: LICENSE
Classifier: Development Status :: 5 - Production/Stable
Classifier: Intended Audience :: Developers
Classifier: Intended Audience :: Information Technology
Classifier: Framework :: AsyncIO
Classifier: License :: OSI Approved :: MIT License
Classifier: Programming Language :: Python
Classifier: Programming Language :: Python :: 3
Classifier: Programming Language :: Python :: 3 :: Only
Classifier: Programming Language :: Python :: 3.10
Classifier: Programming Language :: Python :: 3.11
Classifier: Programming Language :: Python :: 3.12
Classifier: Programming Language :: Python :: 3.13
Classifier: Programming Language :: Python :: Implementation :: CPython
Classifier: Topic :: Software Development :: Libraries :: Python Modules
Classifier: Topic :: Software Development :: Libraries
Classifier: Topic :: Software Development
Classifier: Topic :: System :: Networking
Classifier: Typing :: Typed
Classifier: Operating System :: OS Independent
Requires-Dist: taskiq>=0.11.18
Requires-Dist: ydb>=3.21.12
Requires-Python: >=3.10
Project-URL: Bug Tracker, https://github.com/danfimov/taskiq-ydb/issues
Project-URL: Repository, https://github.com/danfimov/taskiq-ydb/
